quick_token/__init__.py
quick_token/tokenize_it.py
quick_token-0.1.1.dist-info/METADATA
quick_token-0.1.1.dist-info/WHEEL
quick_token-0.1.1.dist-info/RECORD
