Metadata-Version: 2.1
Name: quick-token
Version: 0.1.1
Summary: 
Author: James Allen-Robertson
Author-email: minyall@gmail.com
Requires-Python: >=3.9,<4.0
Classifier: Programming Language :: Python :: 3
Classifier: Programming Language :: Python :: 3.9
Classifier: Programming Language :: Python :: 3.10
Classifier: Programming Language :: Python :: 3.11
Classifier: Programming Language :: Python :: 3.12
Requires-Dist: gensim (>=4.3.3,<5.0.0)
Requires-Dist: pandas (>=2.2.3,<3.0.0)
Requires-Dist: spacy (==3.7.5)
Requires-Dist: tqdm (>=4.66.5,<5.0.0)
